allowedflare/__init__.py
allowedflare/core.py
allowedflare/django.py
allowedflare/jupyter.py
allowedflare/login.html
allowedflare/test_core.py
allowedflare/test_django.py
allowedflare-2024.44.3.dist-info/LICENSE
allowedflare-2024.44.3.dist-info/METADATA
allowedflare-2024.44.3.dist-info/WHEEL
allowedflare-2024.44.3.dist-info/top_level.txt
allowedflare-2024.44.3.dist-info/RECORD
