Metadata-Version: 2.1
Name: allowedflare
Version: 2024.44.3
Summary: Authenticate to Django with JSON Web Tokens (JWTs) signed by Cloudflare Access
Project-URL: Homepage, https://github.com/biobuddies/allowedflare
Classifier: Programming Language :: Python :: 3
Classifier: License :: OSI Approved :: BSD License
Classifier: Operating System :: OS Independent
Classifier: Topic :: Internet :: WWW/HTTP :: Session
License-File: LICENSE
Requires-Dist: cryptography
Requires-Dist: pyjwt
Requires-Dist: requests
Provides-Extra: build
Requires-Dist: build; extra == "build"
Requires-Dist: twine; extra == "build"
Provides-Extra: demo
Requires-Dist: dj-notebook; extra == "demo"
Requires-Dist: django; extra == "demo"
Requires-Dist: django-extensions; extra == "demo"
Requires-Dist: django-health-check; extra == "demo"
Requires-Dist: django-sql-explorer; extra == "demo"
Requires-Dist: djangorestframework; extra == "demo"
Requires-Dist: jupyterlab; extra == "demo"
Provides-Extra: precommit
Requires-Dist: codespell; extra == "precommit"
Requires-Dist: django-stubs; extra == "precommit"
Requires-Dist: djangorestframework-stubs[compatible-mypy]; extra == "precommit"
Requires-Dist: mypy; extra == "precommit"
Requires-Dist: pre-commit; extra == "precommit"
Requires-Dist: ruff; extra == "precommit"
Requires-Dist: shellcheck-py; extra == "precommit"
Requires-Dist: uv; extra == "precommit"
Requires-Dist: yamllint; extra == "precommit"
Provides-Extra: test
Requires-Dist: pytest; extra == "test"
Requires-Dist: pytest-django; extra == "test"
Requires-Dist: pytest-mock; extra == "test"
